gruf/.__init__.py.un~
gruf/__init__.py
gruf-0.0.1.dist-info/METADATA
gruf-0.0.1.dist-info/WHEEL
gruf-0.0.1.dist-info/RECORD
