Metadata-Version: 1.2
Name: gruf
Version: 0.0.1
Summary: a stupid package that does nothing
Home-page: https://github.com/Carreau/gruf
License: UNKNOWN
Author: Matthias Bussonnier
Author-email: bussonniermatthias@gmail.com
Classifier: License :: OSI Approved :: MIT License
